DESCRIPTION.rst
MANIFEST.in
README.md
RELEASE-VERSION
setup.cfg
setup.py
version.py
remote_device/__init__.py
remote_device/remote_device.py
remote_device.egg-info/PKG-INFO
remote_device.egg-info/SOURCES.txt
remote_device.egg-info/dependency_links.txt
remote_device.egg-info/requires.txt
remote_device.egg-info/top_level.txt