Metadata-Version: 1.1
Name: remote-device
Version: 1.0
Summary: Interface to remote devices with auto creation of class methods and auto discovery of available remote devices in Linux, Windows, and Mac OS X
Home-page: https://github.com/JaneliaSciComp/python_remote_device
Author: Peter Polidoro
Author-email: polidorop@janelia.hhmi.org
License: BSD
Keywords: remote serial arduino device
Platform: UNKNOWN
Classifier: Development Status :: 3 - Alpha
Classifier: Intended Audience :: Developers
Classifier: Topic :: Software Development :: Build Tools
Classifier: License :: OSI Approved :: BSD License
Classifier: Programming Language :: Python :: 2.7
